nuropb_gw/README.md
nuropb_gw/__init__.py
nuropb_gw/handler_manager.py
nuropb_gw/handlers/__init__.py
nuropb_gw/handlers/base_handler.py
nuropb_gw/handlers/ws_handler.py
nuropb_gw/service_mesh_manager.py
nuropb_gw/testing/__init__.py
nuropb_gw/testing/stubs.py
nuropb_gw/types.py
nuropb_gw-0.1.4.dist-info/LICENSE
nuropb_gw-0.1.4.dist-info/METADATA
nuropb_gw-0.1.4.dist-info/WHEEL
nuropb_gw-0.1.4.dist-info/entry_points.txt
nuropb_gw-0.1.4.dist-info/RECORD
