Metadata-Version: 2.1
Name: nuropb-gw
Version: 0.1.4
Summary: Websocket gateway library for Nuropb Service Mesh
Home-page: https://github.com/robertbetts/command
License: Apache-2.0
Keywords: python,asynchrous,api,event,rpc,distributed,websockets,sevice-mesh
Author: Robert Betts
Author-email: robert.betts@genoa.io
Requires-Python: >=3.9,<3.12
Classifier: License :: OSI Approved :: Apache Software License
Classifier: Operating System :: OS Independent
Classifier: Programming Language :: Python :: 3
Classifier: Programming Language :: Python :: 3.9
Classifier: Programming Language :: Python :: 3.10
Classifier: Programming Language :: Python :: 3.11
Requires-Dist: nuropb (>=0.1.4,<0.2.0)
Requires-Dist: python-dotenv (>=1.0.0,<2.0.0)
Requires-Dist: tornado (>=6.3.3,<7.0.0)
Project-URL: Repository, https://github.com/robertbetts/command
